src/__init__.py
src/hunt.py
Innovation_Lab_Hunt-0.0.dist-info/METADATA
Innovation_Lab_Hunt-0.0.dist-info/WHEEL
Innovation_Lab_Hunt-0.0.dist-info/top_level.txt
Innovation_Lab_Hunt-0.0.dist-info/RECORD
