Metadata-Version: 2.1
Name: Innovation-Lab-Hunt
Version: 0.0
Summary: Hunt package
Author: PES Innovation Lab
Author-email: innovationlab@pes.edu
